rie_estimator.py
rie_estimator-0.0.4b0.dist-info/LICENSE
rie_estimator-0.0.4b0.dist-info/METADATA
rie_estimator-0.0.4b0.dist-info/WHEEL
rie_estimator-0.0.4b0.dist-info/top_level.txt
rie_estimator-0.0.4b0.dist-info/RECORD
