Metadata-Version: 2.1
Name: rie-estimator
Version: 0.0.4b0
Summary: Function to estimate the oracle RIE corrrelation estimator of a dataset
Home-page: https://github.com/jduarte00/rie_estimator
Author: José Antonio Duarte Mendieta
Author-email: jose.duarte@cimat.mx
Keywords: applied-mathematics finance portfolio-theory correlation-matrices noise-reduction random-matrix-theory
Classifier: Programming Language :: Python :: 3
Classifier: License :: OSI Approved :: GNU General Public License v3 (GPLv3)
Classifier: Topic :: Software Development :: Libraries :: Python Modules
Classifier: Operating System :: OS Independent
Classifier: Intended Audience :: Science/Research
Classifier: Topic :: Scientific/Engineering :: Mathematics
Classifier: Intended Audience :: Financial and Insurance Industry
Classifier: Topic :: Office/Business :: Financial :: Investment
Requires-Python: >=3
License-File: LICENSE
Requires-Dist: pandas
Requires-Dist: numpy
